odoo/addons/attachment_base_synchronize/README.rst
odoo/addons/attachment_base_synchronize/__init__.py
odoo/addons/attachment_base_synchronize/__manifest__.py
odoo/addons/attachment_base_synchronize/data/cron.xml
odoo/addons/attachment_base_synchronize/data/ir_config_parameter.xml
odoo/addons/attachment_base_synchronize/demo/attachment_metadata_demo.xml
odoo/addons/attachment_base_synchronize/i18n/am.po
odoo/addons/attachment_base_synchronize/i18n/ar.po
odoo/addons/attachment_base_synchronize/i18n/attachment_base_synchronize.pot
odoo/addons/attachment_base_synchronize/i18n/bg.po
odoo/addons/attachment_base_synchronize/i18n/bs.po
odoo/addons/attachment_base_synchronize/i18n/ca.po
odoo/addons/attachment_base_synchronize/i18n/cs.po
odoo/addons/attachment_base_synchronize/i18n/da.po
odoo/addons/attachment_base_synchronize/i18n/de.po
odoo/addons/attachment_base_synchronize/i18n/el_GR.po
odoo/addons/attachment_base_synchronize/i18n/en.po
odoo/addons/attachment_base_synchronize/i18n/en_GB.po
odoo/addons/attachment_base_synchronize/i18n/es.po
odoo/addons/attachment_base_synchronize/i18n/es_AR.po
odoo/addons/attachment_base_synchronize/i18n/es_CL.po
odoo/addons/attachment_base_synchronize/i18n/es_CO.po
odoo/addons/attachment_base_synchronize/i18n/es_CR.po
odoo/addons/attachment_base_synchronize/i18n/es_DO.po
odoo/addons/attachment_base_synchronize/i18n/es_EC.po
odoo/addons/attachment_base_synchronize/i18n/es_ES.po
odoo/addons/attachment_base_synchronize/i18n/es_MX.po
odoo/addons/attachment_base_synchronize/i18n/es_PE.po
odoo/addons/attachment_base_synchronize/i18n/es_PY.po
odoo/addons/attachment_base_synchronize/i18n/es_VE.po
odoo/addons/attachment_base_synchronize/i18n/et.po
odoo/addons/attachment_base_synchronize/i18n/eu.po
odoo/addons/attachment_base_synchronize/i18n/fa.po
odoo/addons/attachment_base_synchronize/i18n/fi.po
odoo/addons/attachment_base_synchronize/i18n/fr.po
odoo/addons/attachment_base_synchronize/i18n/fr_CA.po
odoo11_addon_attachment_base_synchronize-11.0.1.0.0.99.dev10.dist-info/METADATA
odoo11_addon_attachment_base_synchronize-11.0.1.0.0.99.dev10.dist-info/WHEEL
odoo11_addon_attachment_base_synchronize-11.0.1.0.0.99.dev10.dist-info/top_level.txt
odoo11_addon_attachment_base_synchronize-11.0.1.0.0.99.dev10.dist-info/RECORD
